nexteraa_glue_jobs/ sedona-agg-logic-job.py
nexteraa_glue_jobs/base_job.py
nexteraa_glue_jobs/script.py
nexteraa_glue_jobs/sedona_job.py
nexteraa_glue_jobs/sedona_logic_job.py
nexteraa_sedona-1.1.0.dist-info/METADATA
nexteraa_sedona-1.1.0.dist-info/WHEEL
nexteraa_sedona-1.1.0.dist-info/top_level.txt
nexteraa_sedona-1.1.0.dist-info/RECORD
